Metadata-Version: 1.2
Name: getadvicetest
Version: 0.0.7
Summary: This is a fancy `Hello World` to publishing Python library to PyPi.
Home-page: UNKNOWN
Author: Rich Leung
Author-email: kleung.hkg@gmail.com
Maintainer: Dimitrios Mangonakis
Maintainer-email: mangonakis@gmail.com
License: UNKNOWN
Platform: UNKNOWN
Requires-Python: >=3.8,<4.0
